architect/__init__.py
architect/core/__init__.py
architect/core/config.py
architect/core/logging.py
architect/core/providers.py
architect/core/schemas.py
architect/core/backends/__init__.py
architect/core/backends/aws_ssm.py
architect/core/backends/base.py
architect/core/backends/local.py
architect/providers/__init__.py
edge_io-0.0.1.dist-info/METADATA
edge_io-0.0.1.dist-info/WHEEL
edge_io-0.0.1.dist-info/top_level.txt
edge_io-0.0.1.dist-info/RECORD
